Topsis_101883055/__init__.py
Topsis_101883055/topsis.py
Topsis_101883055_Naman_Goyal-0.0.2.dist-info/LICENSE
Topsis_101883055_Naman_Goyal-0.0.2.dist-info/METADATA
Topsis_101883055_Naman_Goyal-0.0.2.dist-info/WHEEL
Topsis_101883055_Naman_Goyal-0.0.2.dist-info/top_level.txt
Topsis_101883055_Naman_Goyal-0.0.2.dist-info/RECORD
